nrt_analyzer/__init__.py
nrt_analyzer/data_storage_tools.py
nrt_analyzer/definitions.py
nrt_analyzer/file_tools.py
nrt_analyzer/reader_test.py
nrt_analyzer-0.0.5.dist-info/METADATA
nrt_analyzer-0.0.5.dist-info/WHEEL
nrt_analyzer-0.0.5.dist-info/licenses/LICENSE.txt
nrt_analyzer-0.0.5.dist-info/RECORD
